{
  "project_info": {
    "project_number": "851288471005",
    "firebase_url": "https://upwork-abuturab1.firebaseio.com",
    "project_id": "upwork-abuturab1",
    "storage_bucket": "upwork-abuturab1.appspot.com"
  },
  "client": [
    {
      "client_info": {
        "mobilesdk_app_id": "1:851288471005:android:afd95b2ee076d971dd3234",
        "android_client_info": {
          "package_name": "com.skudentallab.sku"
        }
      },
      "oauth_client": [
        {
          "client_id": "851288471005-10el5dd0n0hr0rc6e162oh34ddvq1duc.apps.googleusercontent.com",
          "client_type": 1,
          "android_info": {
            "package_name": "com.skudentallab.sku",
            "certificate_hash": "11e1618e9657958756cceaa7010efeaf34fe3762"
          }
        },
        {
          "client_id": "851288471005-hc2vser4mr65jjmj1tp5i5kekth5k17q.apps.googleusercontent.com",
          "client_type": 3
        }
      ],
      "api_key": [
        {
          "current_key": "AIzaSyDeiyK8dYGIgG_XMWGPtuZhKdcRYDFj-Z0"
        }
      ],
      "services": {
        "appinvite_service": {
          "other_platform_oauth_client": [
            {
              "client_id": "851288471005-hc2vser4mr65jjmj1tp5i5kekth5k17q.apps.googleusercontent.com",
              "client_type": 3
            }
          ]
        }
      }
    }
  ],
  "configuration_version": "1"
}